MANIFEST.in
README.md
setup.py
pymemc/__init__.py
pymemc/chash.py
pymemc/connpool.py
pymemc/exc.py
pymemc/pymemc.py
pymemc/threadpool.py
pymemc.egg-info/PKG-INFO
pymemc.egg-info/SOURCES.txt
pymemc.egg-info/dependency_links.txt
pymemc.egg-info/top_level.txt