Metadata-Version: 1.0
Name: pymemc
Version: 1.1.4
Summary: Python interface to Memcached.
Home-page: https://github.com/tylerwilliams/pymemc
Author: Tyler Williams
Author-email: williams.tyler@gmail.com
License: UNKNOWN
Download-URL: https://github.com/tylerwilliams/pymemc
Platform: UNKNOWN
